{"id": "cupid_matching.min_distance", "path": "/Users/bernard/Documents/GitHub/cupid-matching/cupid_matching/min_distance.py", "mtime": 1680220879, "size": 11495, "hash": "ce950be3458c411c4da259b17f93ba130466a7579de3b3e1ae92e88733723d53", "data_mtime": 1679789617, "dependencies": ["cupid_matching.entropy", "cupid_matching.matching_utils", "cupid_matching.min_distance_utils", "cupid_matching.utils", "typing", "numpy", "builtins", "abc", "numpy._typing", "numpy._typing._array_like", "numpy._typing._dtype_like", "numpy._typing._nested_sequence", "numpy._typing._ufunc", "numpy.core", "numpy.core.multiarray"], "suppressed": ["scipy.linalg", "scipy.stats", "scipy"], "options": {"disallow_subclassing_any": false, "disable_error_code": [], "warn_no_return": true, "plugins": [], "mypyc": false, "disallow_untyped_decorators": false, "disallow_any_decorated": false, "allow_redefinition": false, "disable_bytearray_promotion": false, "disable_memoryview_promotion": false, "warn_return_any": false, "implicit_reexport": true, "disallow_any_explicit": false, "check_untyped_defs": false, "disabled_error_codes": [], "bazel": false, "platform": "darwin", "ignore_missing_imports": true, "implicit_optional": false, "strict_concatenate": false, "always_false": [], "disallow_any_generics": false, "warn_unreachable": false, "disallow_incomplete_defs": false, "enable_error_code": [], "enabled_error_codes": [], "always_true": [], "strict_equality": false, "disallow_any_expr": false, "disallow_untyped_defs": false, "ignore_errors": false, "strict_optional": true, "warn_unused_ignores": false, "follow_imports_for_stubs": false, "local_partial_types": false, "allow_untyped_globals": false, "follow_imports": "silent", "disallow_any_unimported": false, "disallow_untyped_calls": false}, "dep_prios": [5, 5, 5, 5, 5, 10, 5, 30, 30, 30, 30, 30, 30, 30, 30, 10, 10, 20], "dep_lines": [10, 22, 29, 30, 4, 6, 1, 1, 1, 1, 1, 1, 1, 1, 1, 7, 8, 7], "interface_hash": "036b94427e17b7603b707626522202dcfe429934f60005995d2e13a2eca3d376", "version_id": "1.1.1", "ignore_all": false, "plugin_data": null}